iommi/.DS_Store
iommi/__init__.py
iommi/__init__tests.py
iommi/_db_compat.py
iommi/_db_compat__tests.py
iommi/_web_compat.py
iommi/_web_compat__tests.py
iommi/_web_compat_flask.py
iommi/action.py
iommi/action__tests.py
iommi/admin.py
iommi/admin__tests.py
iommi/apps.py
iommi/asset.py
iommi/asset__tests.py
iommi/attrs.py
iommi/attrs__tests.py
iommi/base.py
iommi/base__tests.py
iommi/code_finder.py
iommi/datetime_parsing.py
iommi/datetime_parsing__tests.py
iommi/debug.py
iommi/debug__tests.py
iommi/docs.py
iommi/docs__tests.py
iommi/edit_table.py
iommi/edit_table__tests.py
iommi/endpoint.py
iommi/endpoint__tests.py
iommi/error.py
iommi/error__tests.py
iommi/evaluate.py
iommi/evaluate__tests.py
iommi/form.py
iommi/form__tests.py
iommi/fragment.py
iommi/fragment__tests.py
iommi/from_model.py
iommi/from_model__tests.py
iommi/live_edit.py
iommi/live_edit__tests.py
iommi/main_menu.py
iommi/main_menu__tests.py
iommi/member.py
iommi/member__tests.py
iommi/menu.py
iommi/menu__tests.py
iommi/model_fields.py
iommi/models.py
iommi/page.py
iommi/page__tests.py
iommi/panel.py
iommi/panel__tests.py
iommi/part.py
iommi/part__tests.py
iommi/path.py
iommi/path__tests.py
iommi/profiling.py
iommi/profiling__tests.py
iommi/query.py
iommi/query__tests.py
iommi/refinable.py
iommi/refinable__tests.py
iommi/shortcut.py
iommi/shortcut__tests.py
iommi/sort_after.py
iommi/sort_after__tests.py
iommi/sql_trace.py
iommi/sql_trace__tests.py
iommi/struct.py
iommi/struct__tests.py
iommi/style.py
iommi/style_98.py
iommi/style__tests.py
iommi/style_base.py
iommi/style_bootstrap.py
iommi/style_bootstrap5.py
iommi/style_bootstrap_docs.py
iommi/style_bootstrap_icons.py
iommi/style_bulma.py
iommi/style_django_admin.py
iommi/style_font_awesome_4.py
iommi/style_font_awesome_6.py
iommi/style_foundation.py
iommi/style_semantic_ui.py
iommi/style_test_base.py
iommi/style_uikit.py
iommi/style_us_web_design_system.py
iommi/style_vanilla_css.py
iommi/style_water.py
iommi/synthetic_traceback.py
iommi-7.22.1.dist-info/licenses/AUTHORS.rst
iommi-7.22.1.dist-info/licenses/LICENSE
iommi-7.22.1.dist-info/METADATA
iommi-7.22.1.dist-info/WHEEL
iommi-7.22.1.dist-info/top_level.txt
iommi-7.22.1.dist-info/RECORD
