Metadata-Version: 2.4
Name: iommi
Version: 7.22.1
Summary: iommi is a high level framework built on django
Home-page: https://github.com/iommirocks/iommi
Author: Anders Hovmöller
Author-email: boxed@killingar.net
License: BSD
Keywords: iommi
Classifier: Development Status :: 5 - Production/Stable
Classifier: Intended Audience :: Developers
Classifier: License :: OSI Approved :: BSD License
Classifier: Natural Language :: English
Classifier: Programming Language :: Python :: 3
License-File: LICENSE
License-File: AUTHORS.rst
Requires-Dist: Django>=3.2
Requires-Dist: pyparsing
Dynamic: author
Dynamic: author-email
Dynamic: classifier
Dynamic: description
Dynamic: home-page
Dynamic: keywords
Dynamic: license
Dynamic: license-file
Dynamic: requires-dist
Dynamic: summary
